adftotxt/__init__.py
adftotxt/adftotxt.py
adftotxt/test.py
adftotxt-0.0.8.dist-info/LICENSE
adftotxt-0.0.8.dist-info/METADATA
adftotxt-0.0.8.dist-info/WHEEL
adftotxt-0.0.8.dist-info/top_level.txt
adftotxt-0.0.8.dist-info/RECORD
